kiphellopip/__init__.py
kiphellopip/main.py
kiphellopip-0.0.1.dist-info/METADATA
kiphellopip-0.0.1.dist-info/WHEEL
kiphellopip-0.0.1.dist-info/top_level.txt
kiphellopip-0.0.1.dist-info/RECORD
