Metadata-Version: 2.4
Name: kiphellopip
Version: 0.0.1
Summary: My first pip module upload drive
Author-email: kip <kkipngenokoech22@gmail.com>
Requires-Python: >=3.8
